aiida_ssh2win/__init__.py
aiida_ssh2win/transport.py
aiida_ssh2win-0.2.0.dist-info/entry_points.txt
aiida_ssh2win-0.2.0.dist-info/LICENSE
aiida_ssh2win-0.2.0.dist-info/WHEEL
aiida_ssh2win-0.2.0.dist-info/METADATA
aiida_ssh2win-0.2.0.dist-info/RECORD
