Metadata-Version: 2.1
Name: aiida-ssh2win
Version: 0.2.0
Summary: A transport plugin allowing AiiDA to run calculations on Windows machines.
Keywords: aiida,plugin
Author-email: Edan Bainglass <edan.bainglass@gmail.com>
Requires-Python: >=3.7
Classifier: Programming Language :: Python
Classifier: Intended Audience :: Science/Research
Classifier: License :: OSI Approved :: MIT License
Classifier: Natural Language :: English
Classifier: Development Status :: 3 - Alpha
Classifier: Framework :: AiiDA
Requires-Dist: aiida-core>=2.0,<3
Requires-Dist: sphinx ; extra == "docs"
Requires-Dist: sphinxcontrib-contentui ; extra == "docs"
Requires-Dist: sphinxcontrib-details-directive ; extra == "docs"
Requires-Dist: furo ; extra == "docs"
Requires-Dist: markupsafe<2.1 ; extra == "docs"
Requires-Dist: pre-commit~=2.2 ; extra == "pre-commit"
Requires-Dist: flake8~=6.0 ; extra == "pre-commit"
Requires-Dist: yapf==0.32 ; extra == "pre-commit"
Requires-Dist: pgtest~=1.3.1 ; extra == "testing"
Requires-Dist: wheel~=0.31 ; extra == "testing"
Requires-Dist: coverage[toml] ; extra == "testing"
Requires-Dist: pytest~=6.0 ; extra == "testing"
Requires-Dist: pytest-cov ; extra == "testing"
Project-URL: Source, https://github.com/edan-bainglass/aiida-ssh2win
Provides-Extra: docs
Provides-Extra: pre-commit
Provides-Extra: testing
